.flake8
.gitignore
.isort.cfg
.pre-commit-config.yaml
LICENSE
README.md
requirements.txt
setup.cfg
setup.py
testcommand.sh
.github/ISSUE_TEMPLATE/bug_report.md
.github/ISSUE_TEMPLATE/feature_request.md
.github/ISSUE_TEMPLATE/question.md
.github/workflows/dist.yml
.github/workflows/pre-commit.yaml
.github/workflows/pytest.yml
.github/workflows/stale.yaml
autofe/__init__.py
autofe/featuretools_iris_test.py
autofe/gbdt_featuretransformer_test.py
autofe/pytorch_tabular_test.py
autofe/pytorchlightning_tabular_test.py
autofe/tab-transformer.py
autofe/feature_engineering/__init__.py
autofe/feature_engineering/feature_generate.py
autofe/feature_engineering/gbdt_feature.py
autofe/tabular_embedding/__init__.py
autofe/tabular_embedding/pytorch_tabular.py
autofe/tabular_embedding/pytorchlightning_tabular.py
autotabular/__init__.py
autotabular/__version__.py
autotabular/automl.py
autotabular/classification.py
autotabular/constants.py
autotabular/ensemble_builder.py
autotabular/estimators.py
autotabular/regression.py
autotabular/requirements.txt
autotabular/smbo.py
autotabular.egg-info/PKG-INFO
autotabular.egg-info/SOURCES.txt
autotabular.egg-info/dependency_links.txt
autotabular.egg-info/requires.txt
autotabular.egg-info/top_level.txt
autotabular/algorithms/__init__.py
autotabular/algorithms/anomaly/__init__.py
autotabular/algorithms/anomaly/abod.py
autotabular/algorithms/anomaly/auto_encoder.py
autotabular/algorithms/anomaly/auto_encoder_torch.py
autotabular/algorithms/anomaly/base.py
autotabular/algorithms/anomaly/base_dl.py
autotabular/algorithms/anomaly/cblof.py
autotabular/algorithms/anomaly/cof.py
autotabular/algorithms/anomaly/combination.py
autotabular/algorithms/anomaly/copod.py
autotabular/algorithms/anomaly/deep_svdd.py
autotabular/algorithms/anomaly/feature_bagging.py
autotabular/algorithms/anomaly/gaal_base.py
autotabular/algorithms/anomaly/hbos.py
autotabular/algorithms/anomaly/iforest.py
autotabular/algorithms/anomaly/knn.py
autotabular/algorithms/anomaly/lmdd.py
autotabular/algorithms/anomaly/loci.py
autotabular/algorithms/anomaly/loda.py
autotabular/algorithms/anomaly/lof.py
autotabular/algorithms/anomaly/lscp.py
