Metadata-Version: 2.1
Name: autotabular
Version: 0.12.0
Summary: Automatic machine learning for tabular data.
Home-page: https://github.com/jianzhnie/AutoTabular
Author: Jianzh Nie
Author-email: jianzhnie@gmail.com
License: Apache License
Keywords: automated machine learning,automl,machine learning,data science,data mining,autotabular
Platform: Linux
Classifier: Environment :: Console
Classifier: Intended Audience :: Developers
Classifier: Intended Audience :: Education
Classifier: Intended Audience :: Science/Research
Classifier: Intended Audience :: Information Technology
Classifier: Natural Language :: English
Classifier: Operating System :: OS Independent
Classifier: Topic :: Scientific/Engineering :: Artificial Intelligence
Classifier: Topic :: Scientific/Engineering :: Information Analysis
Classifier: Programming Language :: Python :: 3.7
Classifier: Programming Language :: Python :: 3.8
Classifier: Programming Language :: Python :: 3.9
Requires-Python: >=3.7
Provides-Extra: test
Provides-Extra: examples
Provides-Extra: docs
License-File: LICENSE
